{
  "id": "bnc-fall-safety-lpt",
  "title": "Fall Prevention & Safe Patient Handling",
  "subtitle": "Basic Nursing Care · keeping clients safe from injury",
  "isFree": false,
  "category": "Basic Nursing Care",
  "domain": "Basic Nursing Care",
  "tracks": [
    "LPT"
  ],
  "format": "mc",
  "tags": [
    "Basic Nursing Care"
  ],
  "scenario": "Preventing falls and moving clients safely on a behavioral-health unit.",
  "steps": [
    {
      "id": 1,
      "type": "single",
      "stepTitle": "Basic Nursing Care",
      "domain": "Basic Nursing Care",
      "q": "Which client factor represents the HIGHEST risk for a fall?",
      "opts": [
        {
          "id": "a",
          "text": "A history of a recent fall",
          "c": true,
          "rat": "A prior recent fall is one of the strongest predictors of another fall."
        },
        {
          "id": "b",
          "text": "Wearing eyeglasses",
          "c": false,
          "rat": "Corrected vision generally reduces, not increases, fall risk."
        },
        {
          "id": "c",
          "text": "Being oriented to person, place, and time",
          "c": false,
          "rat": "Orientation lowers risk compared with confusion."
        },
        {
          "id": "d",
          "text": "Sleeping 8 hours a night",
          "c": false,
          "rat": "Adequate sleep is not a fall-risk factor."
        }
      ]
    },
    {
      "id": 2,
      "type": "single",
      "stepTitle": "Basic Nursing Care",
      "domain": "Basic Nursing Care",
      "q": "Which environmental measure best reduces a client’s fall risk?",
      "opts": [
        {
          "id": "a",
          "text": "Raising all four side rails on the bed",
          "c": false,
          "rat": "Four raised rails can be a restraint and may increase injury if the client climbs over."
        },
        {
          "id": "b",
          "text": "Keeping the bed in a low, locked position with the call light in reach",
          "c": true,
          "rat": "A low, locked bed and an accessible call light are core fall-prevention measures."
        },
        {
          "id": "c",
          "text": "Dimming all lights to help the client rest",
          "c": false,
          "rat": "Poor lighting increases fall risk; a nightlight is safer."
        },
        {
          "id": "d",
          "text": "Placing personal items across the room to encourage walking",
          "c": false,
          "rat": "Out-of-reach items tempt unsafe reaching and ambulation."
        }
      ]
    },
    {
      "id": 3,
      "type": "single",
      "stepTitle": "Basic Nursing Care",
      "domain": "Basic Nursing Care",
      "q": "Using proper body mechanics when assisting a client, the technician should:",
      "opts": [
        {
          "id": "a",
          "text": "Bend at the waist and keep the legs straight",
          "c": false,
          "rat": "Bending at the waist strains the back."
        },
        {
          "id": "b",
          "text": "Bend at the knees and hips, keep the load close, and avoid twisting",
          "c": true,
          "rat": "Using the legs, keeping the load close, and pivoting the feet protect the technician’s back."
        },
        {
          "id": "c",
          "text": "Twist at the trunk to move the client quickly",
          "c": false,
          "rat": "Twisting the trunk under load is a common cause of back injury."
        },
        {
          "id": "d",
          "text": "Hold the client as far from the body as possible",
          "c": false,
          "rat": "Holding a load away from the body increases strain."
        }
      ]
    },
    {
      "id": 4,
      "type": "single",
      "stepTitle": "Basic Nursing Care",
      "domain": "Basic Nursing Care",
      "q": "A client becomes dizzy and begins to fall while walking with the technician. The BEST action is to:",
      "opts": [
        {
          "id": "a",
          "text": "Grab the client’s arm and hold them upright",
          "c": false,
          "rat": "Trying to hold a falling adult fully upright can injure both people."
        },
        {
          "id": "b",
          "text": "Ease the client to the floor while protecting the head, widening your stance",
          "c": true,
          "rat": "Controlled lowering with a wide base of support and head protection is the safest response to an in-progress fall."
        },
        {
          "id": "c",
          "text": "Step away so the client does not pull you down",
          "c": false,
          "rat": "Stepping away leaves the client unprotected."
        },
        {
          "id": "d",
          "text": "Try to catch the client’s full weight",
          "c": false,
          "rat": "Catching full weight risks serious injury to the technician and client."
        }
      ]
    },
    {
      "id": 5,
      "type": "single",
      "stepTitle": "Basic Nursing Care",
      "domain": "Basic Nursing Care",
      "q": "Physical restraints as a fall-prevention measure should be:",
      "opts": [
        {
          "id": "a",
          "text": "Applied routinely to any client at risk of falling",
          "c": false,
          "rat": "Routine restraint is never appropriate and can cause harm."
        },
        {
          "id": "b",
          "text": "A last resort, requiring an order and the least-restrictive option",
          "c": true,
          "rat": "Restraints are a last resort, require a provider order, must be least-restrictive, and are monitored closely."
        },
        {
          "id": "c",
          "text": "Left in place for the entire shift without checks",
          "c": false,
          "rat": "Restrained clients require frequent monitoring and release per policy."
        },
        {
          "id": "d",
          "text": "Used whenever the unit is short-staffed",
          "c": false,
          "rat": "Staffing is never a lawful reason to restrain a client."
        }
      ]
    },
    {
      "id": 6,
      "type": "single",
      "stepTitle": "Basic Nursing Care",
      "domain": "Basic Nursing Care",
      "q": "Immediately after a client falls, the technician should FIRST:",
      "opts": [
        {
          "id": "a",
          "text": "Help the client back into bed right away",
          "c": false,
          "rat": "Moving the client before assessing could worsen an injury."
        },
        {
          "id": "b",
          "text": "Assess the client for injury and check vital signs",
          "c": true,
          "rat": "Assess for injury and obtain vital signs first, then notify the nurse and document/complete an incident report."
        },
        {
          "id": "c",
          "text": "Complete the incident report before anything else",
          "c": false,
          "rat": "Client assessment comes before paperwork."
        },
        {
          "id": "d",
          "text": "Clean the area so no one else falls",
          "c": false,
          "rat": "Client safety assessment takes priority over housekeeping."
        }
      ]
    },
    {
      "id": 7,
      "type": "single",
      "stepTitle": "Basic Nursing Care",
      "domain": "Basic Nursing Care",
      "q": "To reduce falls, clients should be encouraged to wear:",
      "opts": [
        {
          "id": "a",
          "text": "Loose slippers without backs",
          "c": false,
          "rat": "Backless, loose slippers slide off and increase falls."
        },
        {
          "id": "b",
          "text": "Non-slip footwear that fits securely",
          "c": true,
          "rat": "Well-fitting, non-slip footwear improves stability and reduces falls."
        },
        {
          "id": "c",
          "text": "Socks only on smooth floors",
          "c": false,
          "rat": "Plain socks are slippery on hard flooring."
        },
        {
          "id": "d",
          "text": "Sandals with a raised heel",
          "c": false,
          "rat": "Raised heels and open sandals reduce stability."
        }
      ]
    },
    {
      "id": 8,
      "type": "single",
      "stepTitle": "Basic Nursing Care",
      "domain": "Basic Nursing Care",
      "q": "When transferring a weak client from the bed to a chair, the technician should:",
      "opts": [
        {
          "id": "a",
          "text": "Pull the client up by one arm",
          "c": false,
          "rat": "Pulling on one arm can dislocate the shoulder and is unsafe."
        },
        {
          "id": "b",
          "text": "Use a gait/transfer belt and lock the wheels of the bed and chair",
          "c": true,
          "rat": "A transfer belt plus locked wheels provides a secure, controlled transfer."
        },
        {
          "id": "c",
          "text": "Have the client hold onto the IV pole for support",
          "c": false,
          "rat": "IV poles roll and cannot bear weight safely."
        },
        {
          "id": "d",
          "text": "Transfer quickly before the client tires",
          "c": false,
          "rat": "Rushing a transfer increases the risk of a fall."
        }
      ]
    }
  ]
}
