{
  "id": "case-306-lpt",
  "title": "Therapeutic Milieu",
  "subtitle": "The nurse maintains a therapeutic milieu — a safe, structured environment where the unit itself, daily routine, and group activities support healing.",
  "isFree": false,
  "category": "Psychosocial Integrity",
  "domain": "Mental Health Care",
  "tracks": [
    "LPT"
  ],
  "format": "mc",
  "tags": [
    "Health Promotion",
    "Basic Care and Comfort"
  ],
  "scenario": "The nurse maintains a therapeutic milieu — a safe, structured environment where the unit itself, daily routine, and group activities support healing.",
  "steps": [
    {
      "id": 1,
      "type": "single",
      "stepTitle": "Recognize Cues",
      "q": "Which of the following findings is MOST important for the nurse to recognize in this client?",
      "opts": [
        {
          "id": "a",
          "text": "The whole environment supports healing",
          "c": true,
          "rat": "Not just meds."
        },
        {
          "id": "b",
          "text": "Rules should differ from staff to staff",
          "c": false,
          "rat": "Be consistent."
        }
      ],
      "domain": "Mental Health Care"
    },
    {
      "id": 2,
      "type": "single",
      "stepTitle": "Analyze Cues",
      "q": "Which statement BEST explains the significance of this client’s clinical findings?",
      "opts": [
        {
          "id": "a",
          "text": "Only medication matters, not the environment",
          "c": false,
          "rat": "Milieu heals too."
        },
        {
          "id": "b",
          "text": "Clear, consistent limits help patients",
          "c": true,
          "rat": "Same approach."
        }
      ],
      "domain": "Mental Health Care"
    },
    {
      "id": 3,
      "type": "single",
      "stepTitle": "Prioritize Hypotheses",
      "q": "Which is the MOST likely explanation for this client’s presentation?",
      "opts": [
        {
          "id": "a",
          "text": "Encourage involvement in care",
          "c": false,
          "rat": "#4 — Involve."
        },
        {
          "id": "b",
          "text": "Introduce groups and activities",
          "c": false,
          "rat": "#3 — Activities."
        },
        {
          "id": "c",
          "text": "Orient to the routine and unit rules",
          "c": false,
          "rat": "#2 — Structure."
        },
        {
          "id": "d",
          "text": "Ensure a safe environment",
          "c": true,
          "rat": "#1 — Safety."
        }
      ],
      "domain": "Mental Health Care"
    },
    {
      "id": 4,
      "type": "single",
      "stepTitle": "Generate Solutions",
      "q": "Role-modeling calm communication\n\nBased on this finding, the client’s status is BEST classified as:",
      "opts": [
        {
          "id": "a",
          "text": "Supports",
          "c": true,
          "rat": "Therapeutic."
        },
        {
          "id": "b",
          "text": "Undermines",
          "c": false,
          "rat": ""
        }
      ],
      "domain": "Mental Health Care"
    },
    {
      "id": 5,
      "type": "single",
      "stepTitle": "Generate Solutions",
      "q": "Staff giving conflicting messages\n\nBased on this finding, the client’s status is BEST classified as:",
      "opts": [
        {
          "id": "a",
          "text": "Supports",
          "c": false,
          "rat": ""
        },
        {
          "id": "b",
          "text": "Undermines",
          "c": true,
          "rat": "No consistency."
        }
      ],
      "domain": "Mental Health Care"
    },
    {
      "id": 6,
      "type": "single",
      "stepTitle": "Take Action",
      "q": "Which action should the nurse take FIRST?",
      "opts": [
        {
          "id": "a",
          "text": "Restate unit expectations clearly",
          "c": false,
          "rat": "#3 — Limits."
        },
        {
          "id": "b",
          "text": "Help each express feelings appropriately",
          "c": false,
          "rat": "#4 — Process."
        },
        {
          "id": "c",
          "text": "Calmly intervene and lower stimulation",
          "c": false,
          "rat": "#2 — Calm."
        },
        {
          "id": "d",
          "text": "Ensure safety of everyone present",
          "c": true,
          "rat": "#1 — Safety."
        }
      ],
      "domain": "Mental Health Care"
    },
    {
      "id": 7,
      "type": "single",
      "stepTitle": "Evaluate Outcomes",
      "q": "Encouraging participation in groups\n\nBased on this finding, the client’s status is BEST classified as:",
      "opts": [
        {
          "id": "a",
          "text": "Correct",
          "c": true,
          "rat": "Builds skills."
        },
        {
          "id": "b",
          "text": "Incorrect",
          "c": false,
          "rat": ""
        }
      ],
      "domain": "Mental Health Care"
    },
    {
      "id": 8,
      "type": "single",
      "stepTitle": "Evaluate Outcomes",
      "q": "Giving inconsistent messages across shifts\n\nBased on this finding, the client’s status is BEST classified as:",
      "opts": [
        {
          "id": "a",
          "text": "Correct",
          "c": false,
          "rat": ""
        },
        {
          "id": "b",
          "text": "Incorrect",
          "c": true,
          "rat": "Erodes trust."
        }
      ],
      "domain": "Mental Health Care"
    }
  ]
}
