{
  "id": "case-311-lpt",
  "title": "ADHD and Stimulant Therapy",
  "subtitle": "The nurse supports a child with ADHD — inattention, hyperactivity, impulsivity. Give stimulants in the morning, after meals, and monitor growth, appetite, and sleep.",
  "isFree": false,
  "category": "Psychosocial Integrity",
  "domain": "Mental Health Care",
  "tracks": [
    "LPT"
  ],
  "format": "mc",
  "tags": [
    "Health Promotion",
    "Basic Care and Comfort"
  ],
  "scenario": "The nurse supports a child with ADHD — inattention, hyperactivity, impulsivity. Give stimulants in the morning, after meals, and monitor growth, appetite, and sleep.",
  "steps": [
    {
      "id": 1,
      "type": "single",
      "stepTitle": "Recognize Cues",
      "q": "Which of the following findings is MOST important for the nurse to recognize in this client?",
      "opts": [
        {
          "id": "a",
          "text": "Stimulants should be given at bedtime",
          "c": false,
          "rat": "Causes insomnia."
        },
        {
          "id": "b",
          "text": "ADHD involves inattention and hyperactivity",
          "c": true,
          "rat": "Core features."
        }
      ],
      "domain": "Mental Health Care"
    },
    {
      "id": 2,
      "type": "single",
      "stepTitle": "Analyze Cues",
      "q": "Which statement BEST explains the significance of this client’s clinical findings?",
      "opts": [
        {
          "id": "a",
          "text": "Stimulants never affect heart rate",
          "c": false,
          "rat": "Can raise HR/BP."
        },
        {
          "id": "b",
          "text": "Give stimulants after meals",
          "c": true,
          "rat": "Less appetite loss."
        }
      ],
      "domain": "Mental Health Care"
    },
    {
      "id": 3,
      "type": "single",
      "stepTitle": "Prioritize Hypotheses",
      "q": "Which is the MOST likely explanation for this client’s presentation?",
      "opts": [
        {
          "id": "a",
          "text": "Monitor appetite, growth, and vitals",
          "c": false,
          "rat": "#4 — Monitor."
        },
        {
          "id": "b",
          "text": "Take baseline weight, height, and vitals",
          "c": true,
          "rat": "#1 — Baseline."
        },
        {
          "id": "c",
          "text": "Give the dose in the morning after food",
          "c": false,
          "rat": "#2 — Timing."
        },
        {
          "id": "d",
          "text": "Teach the family the schedule",
          "c": false,
          "rat": "#3 — Teach."
        }
      ],
      "domain": "Mental Health Care"
    },
    {
      "id": 4,
      "type": "single",
      "stepTitle": "Generate Solutions",
      "q": "Keeping a consistent daily routine\n\nBased on this finding, the client’s status is BEST classified as:",
      "opts": [
        {
          "id": "a",
          "text": "Helpful",
          "c": true,
          "rat": "Structure."
        },
        {
          "id": "b",
          "text": "Harmful",
          "c": false,
          "rat": ""
        }
      ],
      "domain": "Mental Health Care"
    },
    {
      "id": 5,
      "type": "single",
      "stepTitle": "Generate Solutions",
      "q": "Tracking the child's weight and height\n\nBased on this finding, the client’s status is BEST classified as:",
      "opts": [
        {
          "id": "a",
          "text": "Helpful",
          "c": true,
          "rat": "Growth."
        },
        {
          "id": "b",
          "text": "Harmful",
          "c": false,
          "rat": ""
        }
      ],
      "domain": "Mental Health Care"
    },
    {
      "id": 6,
      "type": "single",
      "stepTitle": "Generate Solutions",
      "q": "Ignoring poor appetite and weight loss\n\nBased on this finding, the client’s status is BEST classified as:",
      "opts": [
        {
          "id": "a",
          "text": "Helpful",
          "c": false,
          "rat": ""
        },
        {
          "id": "b",
          "text": "Harmful",
          "c": true,
          "rat": "Suppression."
        }
      ],
      "domain": "Mental Health Care"
    },
    {
      "id": 7,
      "type": "single",
      "stepTitle": "Take Action",
      "q": "Which action should the nurse take FIRST?",
      "opts": [
        {
          "id": "a",
          "text": "Check weight, growth, and intake",
          "c": false,
          "rat": "#3 — Monitor."
        },
        {
          "id": "b",
          "text": "Assess the dose timing and meals",
          "c": true,
          "rat": "#1 — Assess."
        },
        {
          "id": "c",
          "text": "Notify the provider of the concerns",
          "c": false,
          "rat": "#4 — Notify."
        },
        {
          "id": "d",
          "text": "Confirm the dose is given in the morning",
          "c": false,
          "rat": "#2 — Timing."
        }
      ],
      "domain": "Mental Health Care"
    },
    {
      "id": 8,
      "type": "single",
      "stepTitle": "Evaluate Outcomes",
      "q": "'I will give it right before bed'\n\nBased on this finding, the client’s status is BEST classified as:",
      "opts": [
        {
          "id": "a",
          "text": "Correct",
          "c": false,
          "rat": ""
        },
        {
          "id": "b",
          "text": "Incorrect",
          "c": true,
          "rat": "Insomnia."
        }
      ],
      "domain": "Mental Health Care"
    },
    {
      "id": 9,
      "type": "single",
      "stepTitle": "Evaluate Outcomes",
      "q": "'Stimulants cannot affect his heart rate'\n\nBased on this finding, the client’s status is BEST classified as:",
      "opts": [
        {
          "id": "a",
          "text": "Correct",
          "c": false,
          "rat": ""
        },
        {
          "id": "b",
          "text": "Incorrect",
          "c": true,
          "rat": "Can raise HR/BP."
        }
      ],
      "domain": "Mental Health Care"
    },
    {
      "id": 10,
      "type": "single",
      "stepTitle": "Evaluate Outcomes",
      "q": "'I will give it after breakfast'\n\nBased on this finding, the client’s status is BEST classified as:",
      "opts": [
        {
          "id": "a",
          "text": "Correct",
          "c": true,
          "rat": "Less appetite loss."
        },
        {
          "id": "b",
          "text": "Incorrect",
          "c": false,
          "rat": ""
        }
      ],
      "domain": "Mental Health Care"
    }
  ]
}
