{
  "id": "case-327-lpt",
  "title": "Behavior Modification and Token Economy",
  "subtitle": "The nurse uses behavior modification — reinforcing wanted behavior and not rewarding unwanted behavior — with consistency. A token economy rewards target behaviors.",
  "isFree": false,
  "category": "Psychosocial Integrity",
  "domain": "Mental Health Care",
  "tracks": [
    "LPT"
  ],
  "format": "mc",
  "tags": [
    "Health Promotion",
    "Basic Care and Comfort"
  ],
  "scenario": "The nurse uses behavior modification — reinforcing wanted behavior and not rewarding unwanted behavior — with consistency. A token economy rewards target behaviors.",
  "steps": [
    {
      "id": 1,
      "type": "single",
      "stepTitle": "Recognize Cues",
      "q": "Which of the following findings is MOST important for the nurse to recognize in this client?",
      "opts": [
        {
          "id": "a",
          "text": "Positive reinforcement increases a behavior",
          "c": true,
          "rat": "Adds reward."
        },
        {
          "id": "b",
          "text": "Inconsistent approaches work best",
          "c": false,
          "rat": "Be consistent."
        }
      ],
      "domain": "Mental Health Care"
    },
    {
      "id": 2,
      "type": "single",
      "stepTitle": "Analyze Cues",
      "q": "Which statement BEST explains the significance of this client’s clinical findings?",
      "opts": [
        {
          "id": "a",
          "text": "Giving attention to acting-out reduces it",
          "c": false,
          "rat": "Reinforces it."
        },
        {
          "id": "b",
          "text": "All staff apply the plan the same way",
          "c": true,
          "rat": "Consistency."
        }
      ],
      "domain": "Mental Health Care"
    },
    {
      "id": 3,
      "type": "single",
      "stepTitle": "Prioritize Hypotheses",
      "q": "Which is the MOST likely explanation for this client’s presentation?",
      "opts": [
        {
          "id": "a",
          "text": "Define the clear target behavior",
          "c": true,
          "rat": "#1 — Define."
        },
        {
          "id": "b",
          "text": "Apply it consistently and immediately",
          "c": false,
          "rat": "#4 — Apply."
        },
        {
          "id": "c",
          "text": "Choose meaningful reinforcers",
          "c": false,
          "rat": "#2 — Rewards."
        },
        {
          "id": "d",
          "text": "Explain the plan to patient and staff",
          "c": false,
          "rat": "#3 — Communicate."
        }
      ],
      "domain": "Mental Health Care"
    },
    {
      "id": 4,
      "type": "single",
      "stepTitle": "Generate Solutions",
      "q": "Removing a privilege after rule-breaking\n\nBased on this finding, the client’s status is BEST classified as:",
      "opts": [
        {
          "id": "a",
          "text": "Increases (Reinforce)",
          "c": false,
          "rat": ""
        },
        {
          "id": "b",
          "text": "Decreases",
          "c": true,
          "rat": "Punishment."
        }
      ],
      "domain": "Mental Health Care"
    },
    {
      "id": 5,
      "type": "single",
      "stepTitle": "Generate Solutions",
      "q": "Giving a token for completing a goal\n\nBased on this finding, the client’s status is BEST classified as:",
      "opts": [
        {
          "id": "a",
          "text": "Increases (Reinforce)",
          "c": true,
          "rat": "Reward."
        },
        {
          "id": "b",
          "text": "Decreases",
          "c": false,
          "rat": ""
        }
      ],
      "domain": "Mental Health Care"
    },
    {
      "id": 6,
      "type": "single",
      "stepTitle": "Take Action",
      "q": "Which action should the nurse take FIRST?",
      "opts": [
        {
          "id": "a",
          "text": "Reinforce appropriate behavior when it occurs",
          "c": false,
          "rat": "#3 — Reward good."
        },
        {
          "id": "b",
          "text": "Apply the plan consistently with the team",
          "c": false,
          "rat": "#4 — Consistency."
        },
        {
          "id": "c",
          "text": "Ensure safety",
          "c": true,
          "rat": "#1 — Safety."
        },
        {
          "id": "d",
          "text": "Avoid reinforcing the behavior with attention",
          "c": false,
          "rat": "#2 — Extinction."
        }
      ],
      "domain": "Mental Health Care"
    },
    {
      "id": 7,
      "type": "single",
      "stepTitle": "Evaluate Outcomes",
      "q": "Keeping the plan consistent across shifts\n\nBased on this finding, the client’s status is BEST classified as:",
      "opts": [
        {
          "id": "a",
          "text": "Correct",
          "c": true,
          "rat": "Consistency."
        },
        {
          "id": "b",
          "text": "Incorrect",
          "c": false,
          "rat": ""
        }
      ],
      "domain": "Mental Health Care"
    },
    {
      "id": 8,
      "type": "single",
      "stepTitle": "Evaluate Outcomes",
      "q": "Rewarding unwanted behavior to keep peace\n\nBased on this finding, the client’s status is BEST classified as:",
      "opts": [
        {
          "id": "a",
          "text": "Correct",
          "c": false,
          "rat": ""
        },
        {
          "id": "b",
          "text": "Incorrect",
          "c": true,
          "rat": "Strengthens it."
        }
      ],
      "domain": "Mental Health Care"
    }
  ]
}
